zymodbustcpclient/__init__.py
zymodbustcpclient/example.py
zymylogger/__init__.py
zymylogger/zymylogger.py
zymysql/__init__.py
zymysql/zymysql.py
zymysql-0.3.dist-info/METADATA
zymysql-0.3.dist-info/WHEEL
zymysql-0.3.dist-info/top_level.txt
zymysql-0.3.dist-info/RECORD
