Metadata-Version: 2.1
Name: zymysql
Version: 0.3
Summary: UNKNOWN
Home-page: UNKNOWN
Author: zhang yue
License: UNKNOWN
Platform: UNKNOWN
Requires-Dist: pymysql
